arxette/__init__.py
arxette/arx.py
arxette/garch.py
arxette-0.2.0.dist-info/LICENSE
arxette-0.2.0.dist-info/METADATA
arxette-0.2.0.dist-info/WHEEL
arxette-0.2.0.dist-info/top_level.txt
arxette-0.2.0.dist-info/RECORD
