Metadata-Version: 2.1
Name: arxette
Version: 0.2.0
Summary: autoregressive fit
Requires-Python: >=3.10
License-File: LICENSE
Requires-Dist: jax >=0.4.35
Requires-Dist: numpy >=2.1.2
Requires-Dist: scipy >=1.14.1
